{
  "timestamp": "2023-11-12T08:05:39Z",
  "previous_timestamp": "2023-11-12T08:00:41Z",
  "next_timestamp": "2023-11-12T08:10:40Z",
  "data": {
    "id": "220b35d0541d11afe06b0f35c087518d",
    "sport_key": "basketball_nba",
    "sport_title": "NBA",
    "commence_time": "2023-11-12T20:10:00Z",
    "home_team": "Brooklyn Nets",
    "away_team": "Washington Wizards",
    "bookmakers": [
      {
        "key": "draftkings",
        "title": "DraftKings",
        "last_update": "2023-11-12T08:05:08Z",
        "markets": [
          {
            "key": "player_points",
            "last_update": "2023-11-12T08:06:37Z",
            "outcomes": [
              {
                "name": "Over",
                "description": "Daniel Gafford",
                "price": 1.95,
                "point": 9.5
              },
              {
                "name": "Under",
                "description": "Daniel Gafford",
                "price": 1.8,
                "point": 9.5
              },
              {
                "name": "Over",
                "description": "Deni Avdija",
                "price": 1.95,
                "point": 11.5
              },
              {
                "name": "Under",
                "description": "Deni Avdija",
                "price": 1.83,
                "point": 11.5
              },
              {
                "name": "Over",
                "description": "Dorian Finney-Smith",
                "price": 1.95,
                "point": 11.5
              },
              {
                "name": "Under",
                "description": "Dorian Finney-Smith",
                "price": 1.8,
                "point": 11.5
              },
              {
                "name": "Over",
                "description": "Jordan Poole",
                "price": 1.95,
                "point": 17.5
              },
              {
                "name": "Under",
                "description": "Jordan Poole",
                "price": 1.83,
                "point": 17.5
              },
              {
                "name": "Over",
                "description": "Kyle Kuzma",
                "price": 1.87,
                "point": 23.5
              },
              {
                "name": "Under",
                "description": "Kyle Kuzma",
                "price": 1.87,
                "point": 23.5
              },
              {
                "name": "Over",
                "description": "Mikal Bridges",
                "price": 1.95,
                "point": 24.5
              },
              {
                "name": "Under",
                "description": "Mikal Bridges",
                "price": 1.83,
                "point": 24.5
              },
              {
                "name": "Over",
                "description": "Spencer Dinwiddie",
                "price": 1.83,
                "point": 12.5
              },
              {
                "name": "Under",
                "description": "Spencer Dinwiddie",
                "price": 1.95,
                "point": 12.5
              },
              {
                "name": "Over",
                "description": "Tyus Jones",
                "price": 1.77,
                "point": 9.5
              },
              {
                "name": "Under",
                "description": "Tyus Jones",
                "price": 2.0,
                "point": 9.5
              }
            ]
          }
        ]
      },
      {
        "key": "betonlineag",
        "title": "BetOnline.ag",
        "last_update": "2023-11-12T08:04:52Z",
        "markets": [
          {
            "key": "player_points",
            "last_update": "2023-11-12T08:05:29Z",
            "outcomes": [
              {
                "name": "Over",
                "description": "Spencer Dinwiddie",
                "price": 1.82,
                "point": 12.5
              },
              {
                "name": "Under",
                "description": "Spencer Dinwiddie",
                "price": 1.94,
                "point": 12.5
              },
              {
                "name": "Over",
                "description": "Deni Avdija",
                "price": 1.95,
                "point": 11.5
              },
              {
                "name": "Under",
                "description": "Deni Avdija",
                "price": 1.81,
                "point": 11.5
              },
              {
                "name": "Over",
                "description": "Daniel Gafford",
                "price": 1.97,
                "point": 9.5
              },
              {
                "name": "Under",
                "description": "Daniel Gafford",
                "price": 1.8,
                "point": 9.5
              },
              {
                "name": "Under",
                "description": "Kyle Kuzma",
                "price": 1.87,
                "point": 23.5
              },
              {
                "name": "Over",
                "description": "Kyle Kuzma",
                "price": 1.89,
                "point": 23.5
              },
              {
                "name": "Over",
                "description": "Mikal Bridges",
                "price": 1.92,
                "point": 24.5
              },
              {
                "name": "Under",
                "description": "Mikal Bridges",
                "price": 1.84,
                "point": 24.5
              },
              {
                "name": "Under",
                "description": "Dorian Finney-Smith",
                "price": 1.8,
                "point": 11.5
              },
              {
                "name": "Over",
                "description": "Dorian Finney-Smith",
                "price": 1.97,
                "point": 11.5
              },
              {
                "name": "Under",
                "description": "Tyus Jones",
                "price": 1.77,
                "point": 10.5
              },
              {
                "name": "Over",
                "description": "Tyus Jones",
                "price": 2.0,
                "point": 10.5
              },
              {
                "name": "Under",
                "description": "Jordan Poole",
                "price": 1.82,
                "point": 17.5
              },
              {
                "name": "Over",
                "description": "Jordan Poole",
                "price": 1.94,
                "point": 17.5
              }
            ]
          }
        ]
      },
      {
        "key": "williamhill_us",
        "title": "Caesars",
        "last_update": "2023-11-12T08:02:50Z",
        "markets": [
          {
            "key": "player_points",
            "last_update": "2023-11-12T08:05:34Z",
            "outcomes": [
              {
                "name": "Over",
                "description": "Daniel Gafford",
                "price": 1.96,
                "point": 9.5
              },
              {
                "name": "Under",
                "description": "Daniel Gafford",
                "price": 1.76,
                "point": 9.5
              },
              {
                "name": "Over",
                "description": "Mikal Bridges",
                "price": 1.87,
                "point": 24.5
              },
              {
                "name": "Under",
                "description": "Mikal Bridges",
                "price": 1.84,
                "point": 24.5
              },
              {
                "name": "Over",
                "description": "Kyle Kuzma",
                "price": 1.84,
                "point": 23.5
              },
              {
                "name": "Under",
                "description": "Kyle Kuzma",
                "price": 1.87,
                "point": 23.5
              },
              {
                "name": "Over",
                "description": "Deni Avdija",
                "price": 1.9,
                "point": 11.5
              },
              {
                "name": "Under",
                "description": "Deni Avdija",
                "price": 1.81,
                "point": 11.5
              },
              {
                "name": "Over",
                "description": "Spencer Dinwiddie",
                "price": 1.76,
                "point": 12.5
              },
              {
                "name": "Under",
                "description": "Spencer Dinwiddie",
                "price": 1.96,
                "point": 12.5
              },
              {
                "name": "Over",
                "description": "Dorian Finney-Smith",
                "price": 1.93,
                "point": 11.5
              },
              {
                "name": "Under",
                "description": "Dorian Finney-Smith",
                "price": 1.79,
                "point": 11.5
              },
              {
                "name": "Over",
                "description": "Tyus Jones",
                "price": 1.75,
                "point": 9.5
              },
              {
                "name": "Under",
                "description": "Tyus Jones",
                "price": 1.97,
                "point": 9.5
              },
              {
                "name": "Over",
                "description": "Jordan Poole",
                "price": 1.93,
                "point": 17.5
              },
              {
                "name": "Under",
                "description": "Jordan Poole",
                "price": 1.79,
                "point": 17.5
              }
            ]
          }
        ]
      },
      {
        "key": "fanduel",
        "title": "FanDuel",
        "last_update": "2023-11-12T08:02:47Z",
        "markets": [
          {
            "key": "player_points",
            "last_update": "2023-11-12T08:05:16Z",
            "outcomes": [
              {
                "name": "Over",
                "description": "Jordan Poole",
                "price": 1.96,
                "point": 17.5
              },
              {
                "name": "Under",
                "description": "Jordan Poole",
                "price": 1.82,
                "point": 17.5
              },
              {
                "name": "Over",
                "description": "Mikal Bridges",
                "price": 1.93,
                "point": 24.5
              },
              {
                "name": "Under",
                "description": "Mikal Bridges",
                "price": 1.85,
                "point": 24.5
              },
              {
                "name": "Over",
                "description": "Deni Avdija",
                "price": 2.0,
                "point": 11.5
              },
              {
                "name": "Under",
                "description": "Deni Avdija",
                "price": 1.78,
                "point": 11.5
              },
              {
                "name": "Over",
                "description": "Spencer Dinwiddie",
                "price": 1.82,
                "point": 12.5
              },
              {
                "name": "Under",
                "description": "Spencer Dinwiddie",
                "price": 1.96,
                "point": 12.5
              },
              {
                "name": "Over",
                "description": "Dorian Finney-Smith",
                "price": 1.98,
                "point": 11.5
              },
              {
                "name": "Under",
                "description": "Dorian Finney-Smith",
                "price": 1.8,
                "point": 11.5
              },
              {
                "name": "Over",
                "description": "Tyus Jones",
                "price": 1.78,
                "point": 9.5
              },
              {
                "name": "Under",
                "description": "Tyus Jones",
                "price": 2.0,
                "point": 9.5
              },
              {
                "name": "Over",
                "description": "Daniel Gafford",
                "price": 2.0,
                "point": 9.5
              },
              {
                "name": "Under",
                "description": "Daniel Gafford",
                "price": 1.78,
                "point": 9.5
              },
              {
                "name": "Over",
                "description": "Kyle Kuzma",
                "price": 1.8,
                "point": 22.5
              },
              {
                "name": "Under",
                "description": "Kyle Kuzma",
                "price": 1.98,
                "point": 22.5
              }
            ]
          }
        ]
      },
      {
        "key": "pointsbetus",
        "title": "PointsBet (US)",
        "last_update": "2023-11-12T08:04:34Z",
        "markets": [
          {
            "key": "player_points",
            "last_update": "2023-11-12T08:01:55Z",
            "outcomes": [
              {
                "name": "Over",
                "description": "Daniel Gafford",
                "price": 1.91,
                "point": 9.5
              },
              {
                "name": "Under",
                "description": "Daniel Gafford",
                "price": 1.83,
                "point": 9.5
              },
              {
                "name": "Over",
                "description": "Deni Avdija",
                "price": 1.91,
                "point": 11.5
              },
              {
                "name": "Under",
                "description": "Deni Avdija",
                "price": 1.83,
                "point": 11.5
              },
              {
                "name": "Over",
                "description": "Dorian Finney-Smith",
                "price": 1.95,
                "point": 11.5
              },
              {
                "name": "Under",
                "description": "Dorian Finney-Smith",
                "price": 1.8,
                "point": 11.5
              },
              {
                "name": "Over",
                "description": "Jordan Poole",
                "price": 1.91,
                "point": 17.5
              },
              {
                "name": "Under",
                "description": "Jordan Poole",
                "price": 1.83,
                "point": 17.5
              },
              {
                "name": "Over",
                "description": "Kyle Kuzma",
                "price": 1.87,
                "point": 23.5
              },
              {
                "name": "Under",
                "description": "Kyle Kuzma",
                "price": 1.87,
                "point": 23.5
              },
              {
                "name": "Over",
                "description": "Mikal Bridges",
                "price": 1.87,
                "point": 24.5
              },
              {
                "name": "Under",
                "description": "Mikal Bridges",
                "price": 1.87,
                "point": 24.5
              },
              {
                "name": "Over",
                "description": "Spencer Dinwiddie",
                "price": 1.83,
                "point": 12.5
              },
              {
                "name": "Under",
                "description": "Spencer Dinwiddie",
                "price": 1.91,
                "point": 12.5
              },
              {
                "name": "Over",
                "description": "Tyus Jones",
                "price": 1.77,
                "point": 9.5
              },
              {
                "name": "Under",
                "description": "Tyus Jones",
                "price": 2.0,
                "point": 9.5
              }
            ]
          }
        ]
      },
      {
        "key": "bovada",
        "title": "Bovada",
        "last_update": "2023-11-12T08:03:48Z",
        "markets": [
          {
            "key": "player_points",
            "last_update": "2023-11-12T08:05:42Z",
            "outcomes": [
              {
                "name": "Over",
                "description": "Daniel Gafford",
                "price": 1.95,
                "point": 9.5
              },
              {
                "name": "Under",
                "description": "Daniel Gafford",
                "price": 1.8,
                "point": 9.5
              },
              {
                "name": "Over",
                "description": "Deni Avdija",
                "price": 1.95,
                "point": 11.5
              },
              {
                "name": "Under",
                "description": "Deni Avdija",
                "price": 1.8,
                "point": 11.5
              },
              {
                "name": "Over",
                "description": "Dorian Finney Smith",
                "price": 1.95,
                "point": 11.5
              },
              {
                "name": "Under",
                "description": "Dorian Finney Smith",
                "price": 1.8,
                "point": 11.5
              },
              {
                "name": "Over",
                "description": "Jordan Poole",
                "price": 1.95,
                "point": 17.5
              },
              {
                "name": "Under",
                "description": "Jordan Poole",
                "price": 1.8,
                "point": 17.5
              },
              {
                "name": "Over",
                "description": "Kyle Kuzma",
                "price": 1.74,
                "point": 22.5
              },
              {
                "name": "Under",
                "description": "Kyle Kuzma",
                "price": 2.05,
                "point": 22.5
              },
              {
                "name": "Over",
                "description": "Mikal Bridges",
                "price": 1.95,
                "point": 24.5
              },
              {
                "name": "Under",
                "description": "Mikal Bridges",
                "price": 1.8,
                "point": 24.5
              },
              {
                "name": "Over",
                "description": "Spencer Dinwiddie",
                "price": 1.8,
                "point": 12.5
              },
              {
                "name": "Under",
                "description": "Spencer Dinwiddie",
                "price": 1.95,
                "point": 12.5
              },
              {
                "name": "Over",
                "description": "Tyus Jones",
                "price": 1.74,
                "point": 9.5
              },
              {
                "name": "Under",
                "description": "Tyus Jones",
                "price": 2.05,
                "point": 9.5
              }
            ]
          }
        ]
      },
      {
        "key": "barstool",
        "title": "Barstool Sportsbook",
        "last_update": "2023-11-12T08:03:37Z",
        "markets": [
          {
            "key": "player_points",
            "last_update": "2023-11-12T08:06:33Z",
            "outcomes": [
              {
                "name": "Over",
                "description": "Kyle Kuzma",
                "price": 1.91,
                "point": 23.5
              },
              {
                "name": "Under",
                "description": "Kyle Kuzma",
                "price": 1.83,
                "point": 23.5
              },
              {
                "name": "Over",
                "description": "Mikal Bridges",
                "price": 1.95,
                "point": 24.5
              },
              {
                "name": "Under",
                "description": "Mikal Bridges",
                "price": 1.8,
                "point": 24.5
              },
              {
                "name": "Over",
                "description": "Jordan Poole",
                "price": 1.87,
                "point": 17.5
              },
              {
                "name": "Under",
                "description": "Jordan Poole",
                "price": 1.87,
                "point": 17.5
              },
              {
                "name": "Over",
                "description": "Spencer Dinwiddie",
                "price": 1.8,
                "point": 12.5
              },
              {
                "name": "Under",
                "description": "Spencer Dinwiddie",
                "price": 1.95,
                "point": 12.5
              },
              {
                "name": "Over",
                "description": "Dorian Finney-Smith",
                "price": 1.95,
                "point": 11.5
              },
              {
                "name": "Under",
                "description": "Dorian Finney-Smith",
                "price": 1.8,
                "point": 11.5
              },
              {
                "name": "Over",
                "description": "Deni Avdija",
                "price": 1.91,
                "point": 11.5
              },
              {
                "name": "Under",
                "description": "Deni Avdija",
                "price": 1.83,
                "point": 11.5
              },
              {
                "name": "Over",
                "description": "Tyus Jones",
                "price": 1.74,
                "point": 9.5
              },
              {
                "name": "Under",
                "description": "Tyus Jones",
                "price": 2.05,
                "point": 9.5
              },
              {
                "name": "Over",
                "description": "Daniel Gafford",
                "price": 1.95,
                "point": 9.5
              },
              {
                "name": "Under",
                "description": "Daniel Gafford",
                "price": 1.8,
                "point": 9.5
              }
            ]
          }
        ]
      }
    ]
  }
}